octopus_kernel/__init__.py
octopus_kernel/kernel/__init__.py
octopus_kernel/kernel/config.py
octopus_kernel/kernel/kernel_app.py
octopus_kernel/kernel/kernel_client.py
octopus_kernel/kernel/kernel_mgr.py
octopus_kernel/kernel/launch_kernel.py
octopus_kernel/server/__init__.py
octopus_kernel/server/kernel_env_sample.py
octopus_kernel/server/kernel_rpc_server.py
octopus_kernel-0.4.18.dist-info/METADATA
octopus_kernel-0.4.18.dist-info/WHEEL
octopus_kernel-0.4.18.dist-info/entry_points.txt
octopus_kernel-0.4.18.dist-info/top_level.txt
octopus_kernel-0.4.18.dist-info/RECORD
