Metadata-Version: 2.1
Name: octopus-kernel
Version: 0.4.18
Summary: Open source code interpreter agent for LLM
Home-page: https://github.com/dbpunk-labs/octopus
Author: imotai
Author-email: wangtaize@dbpunk.com
Requires-Dist: octopus-proto
Requires-Dist: grpc-google-iam-v1 >=0.12.6
Requires-Dist: grpcio-tools >=1.57.0
Requires-Dist: ipykernel >=6.25.1
Requires-Dist: jupyter-client >=8.3.0
Requires-Dist: matplotlib >=3.7.2
Requires-Dist: pandas
Requires-Dist: numpy
